<?xml version="1.0" encoding="ISO-8859-1" standalone="yes"?>
<?xml-stylesheet type="text/xsl" href="../../../clonk.xsl"?>
<clonkDoc xmlns="https://clonkspot.org"
      xmlns:xsi="http://www.w3.org/2001/XMLSchema-instance"
          xsi:schemaLocation="https://clonkspot.org ../../../clonk.xsd" xml:lang="de">
	<func>
		<title>CastObjects</title>
		<category>Objekte/Erzeugung</category>
		<versions><version>4.6.5.0 CP</version></versions>
		<syntax>
			<rtype>void</rtype>
			<params>
				<param><type>id</type><name>id</name><desc>ID des Objekttyps, der verschleudert wird</desc></param>
				<param><type>int</type><name>iNumber</name><desc>Anzahl verschleuderter Objekte.</desc></param>
				<param><type>int</type><name>iLevel</name><desc>Geschwindigkeit der verschleuderten Objekte</desc></param>
				<param><type>int</type><name>iX</name><desc>X-Ausgangsposition. Offset zum aufrufenden Objekt bei lokalem Aufruf.</desc><optional /></param>
				<param><type>int</type><name>iY</name><desc>Y-Ausgangsposition. Offset zum aufrufenden Objekt bei lokalem Aufruf.</desc><optional /></param>
			</params>
		</syntax>
		<desc>Verschleudert iNumber Objekte an angegebener Position mit einer Geschwindigkeit von iLevel. Bei einem lokalen Aufruf haben die erzeugten Objekte den selben Besitzer wie das aufrufende Objekt.</desc>
		<examples>
			<example>
				<code>var num=<funcLink>GetVertexNum</funcLink>()<emLink href="script/operatoren.html">-</emLink>1;
CastObjects(SPRK,1,20,<funcLink>GetVertex</funcLink>(num, 0)<emLink href="script/operatoren.html">-</emLink><funcLink>GetX</funcLink>(), <funcLink>GetVertex</funcLink>(num, 1)<emLink href="script/operatoren.html">-</emLink><funcLink>GetY</funcLink>());
				</code>
				<text>Erzeugt am letzten Vertex einer Linie einen Funken. Bei mehrmaligem Aufruf erzielt man damit den gleichen Effekt wie bei einem Blitzeinschlag.</text>
			</example>
		</examples>
		<related>
			<funcLink>CreateObject</funcLink>
		</related>
	</func>
	<author>Günther</author><date>2002-02</date>
</clonkDoc>
