<?xml version="1.0" encoding="ISO-8859-1" standalone="yes"?>
<?xml-stylesheet type="text/xsl" href="../../../clonk.xsl"?>
<clonkDoc xmlns="https://clonkspot.org"
      xmlns:xsi="http://www.w3.org/2001/XMLSchema-instance"
          xsi:schemaLocation="https://clonkspot.org ../../../clonk.xsd" xml:lang="de">
	<func>
		<title>SetFilmView</title>
		<category>Spieler/Sicht</category>
		<versions><version>4.9.1.0 GWE</version></versions>
		<syntax>
			<rtype>int</rtype>
			<params>
				<param><type>int</type><name>iToPlr</name><desc>Nummer des Spielers, dessen Sicht gezeigt werden soll.</desc></param>
			</params>
		</syntax>
		<desc>Setzt die Sicht in Filmwiedergaben auf den angegebenen Spieler.</desc>
		<examples>
			<example>
<code>protected func InitializePlayer(iPlr)
{
	<funclink>if</funclink> (<funclink>GetPlayerName</funclink>(iPlr) eq "Kamera") SetFilmView(iPlr);
}</code>
				<text>Dieses Szenarioscript setzt die Sicht in der Wiedergabe der aufgenommenen Runde auf den Spieler mit dem Namen "Kamera".</text>
			</example>
		</examples>
	</func>
	<author>Sven2</author><date>2002-05</date>
</clonkDoc>
